dbt/__init__.py
dbt/adapters/gaussdbdws/__init__.py
dbt/adapters/gaussdbdws/__version__.py
dbt/adapters/gaussdbdws/column.py
dbt/adapters/gaussdbdws/connections.py
dbt/adapters/gaussdbdws/impl.py
dbt/adapters/gaussdbdws/relation.py
dbt/adapters/gaussdbdws/record/__init__.py
dbt/adapters/gaussdbdws/record/handle.py
dbt/adapters/gaussdbdws/record/cursor/cursor.py
dbt/adapters/gaussdbdws/record/cursor/status.py
dbt/adapters/gaussdbdws/relation_configs/__init__.py
dbt/adapters/gaussdbdws/relation_configs/constants.py
dbt/adapters/gaussdbdws/relation_configs/index.py
dbt/adapters/gaussdbdws/relation_configs/materialized_view.py
dbt/include/gaussdbdws/__init__.py
dbt/include/gaussdbdws/dbt_project.yml
dbt/include/gaussdbdws/profile_template.yml
dbt/include/gaussdbdws/sample_profiles.yml
dbt/include/gaussdbdws/macros/adapters.sql
dbt/include/gaussdbdws/macros/catalog.sql
dbt/include/gaussdbdws/macros/relations.sql
dbt/include/gaussdbdws/macros/timestamps.sql
dbt/include/gaussdbdws/macros/materializations/incremental_strategies.sql
dbt/include/gaussdbdws/macros/materializations/snapshot_merge.sql
dbt/include/gaussdbdws/macros/relations/materialized_view/alter.sql
dbt/include/gaussdbdws/macros/relations/materialized_view/create.sql
dbt/include/gaussdbdws/macros/relations/materialized_view/describe.sql
dbt/include/gaussdbdws/macros/relations/materialized_view/drop.sql
dbt/include/gaussdbdws/macros/relations/materialized_view/refresh.sql
dbt/include/gaussdbdws/macros/relations/materialized_view/rename.sql
dbt/include/gaussdbdws/macros/relations/table/drop.sql
dbt/include/gaussdbdws/macros/relations/table/rename.sql
dbt/include/gaussdbdws/macros/relations/table/replace.sql
dbt/include/gaussdbdws/macros/relations/view/drop.sql
dbt/include/gaussdbdws/macros/relations/view/rename.sql
dbt/include/gaussdbdws/macros/relations/view/replace.sql
dbt/include/gaussdbdws/macros/utils/any_value.sql
dbt/include/gaussdbdws/macros/utils/dateadd.sql
dbt_gaussdbdws-1.0.1.dist-info/METADATA
dbt_gaussdbdws-1.0.1.dist-info/WHEEL
dbt_gaussdbdws-1.0.1.dist-info/licenses/LICENSE
dbt_gaussdbdws-1.0.1.dist-info/RECORD
